gravity_interface/__init__.py
gravity_interface/launcher.py
gravity_interface/main_operator.py
gravity_interface/modules.py
gravity_interface/sqlCommands.py
gravity_interface/terminal.py
gravity_interface/wlistener.py
gravity_interface/configs/__init__.py
gravity_interface/configs/config.py
gravity_interface/configs/settings.py
gravity_interface/imgs/__init__.py
gravity_interface/imgs/abort.png
gravity_interface/imgs/abortFiltres.png
gravity_interface/imgs/abortFiltresZ.png
gravity_interface/imgs/abortZ.png
gravity_interface/imgs/accept.png
gravity_interface/imgs/acceptZ.png
gravity_interface/imgs/addComm.png
gravity_interface/imgs/auto_gate_control.png
gravity_interface/imgs/auto_gate_controlZ.png
gravity_interface/imgs/backscreen — копия.png
gravity_interface/imgs/backscreen.png
gravity_interface/imgs/calendarwin.png
gravity_interface/imgs/cancel.png
gravity_interface/imgs/cancelZ.png
gravity_interface/imgs/car_in.png
gravity_interface/imgs/car_out.png
gravity_interface/imgs/change.png
gravity_interface/imgs/changeZ.png
gravity_interface/imgs/chatDecline.png
gravity_interface/imgs/chatbg.png
gravity_interface/imgs/chatcommit.png
gravity_interface/imgs/chatexit.png
gravity_interface/imgs/chaticon.png
gravity_interface/imgs/choosePol.png
gravity_interface/imgs/close.png
gravity_interface/imgs/closeZ.png
gravity_interface/imgs/close_recs.png
gravity_interface/imgs/currentEvents.png
gravity_interface/imgs/decline.png
gravity_interface/imgs/declineZ.png
gravity_interface/imgs/disputswin.png
gravity_interface/imgs/ensureCloseRec.png
gravity_interface/imgs/enter.png
gravity_interface/imgs/enterZ.png
gravity_interface/imgs/exit.png
gravity_interface/imgs/exitZ.png
gravity_interface/imgs/exitwin.png
gravity_interface/imgs/fakeTree.png
gravity_interface/imgs/forbwin.png
gravity_interface/imgs/frontscreen.png
gravity_interface/imgs/gateL.png
gravity_interface/imgs/gateR.png
gravity_interface/imgs/gate_arrow.png
gravity_interface/imgs/gate_base.png
gravity_interface_hd-1.343.dist-info/METADATA
gravity_interface_hd-1.343.dist-info/WHEEL
gravity_interface_hd-1.343.dist-info/top_level.txt
gravity_interface_hd-1.343.dist-info/RECORD
