Metadata-Version: 2.1
Name: gravity-interface-hd
Version: 1.343
Summary: UNKNOWN
Home-page: UNKNOWN
Author: PunchyArchy
Author-email: ksmdrmvscthny@gmail.com
License: UNKNOWN
Platform: UNKNOWN
Requires-Dist: pillow
Requires-Dist: pyscreenshot
Requires-Dist: tkcalendar
Requires-Dist: screeninfo
